Workbook

Sheet Data
A1: Customer_ID | B1: Customer_Name | C1: Region | D1: Product_Category | E1: Sales | F1: Quantity | G1: Discount | H1: Order_Date | I1: Profit
A2: CUST019 | B2: James Davis | C2: West | D2: Books | E2: 1036.09 | F2: 4 | G2: 0.2 | H2: 2024-04-10 | I2: 331.55
A3: CUST012 | B3: Robert Anderson | C3: West | D3: Clothing | E3: 1101.28 | F3: 3 | G3: 0.2 | H3: 2024-04-11 | I3: 440.51
A4: CUST017 | B4: James Taylor | C4: East | D4: Books | E4: 713.34 | F4: 17 | G4: 0 | H4: 2024-04-14 | I4: 285.34
A5: CUST005 | B5: Robert Anderson | C5: South | D5: Electronics | E5: 760.93 | F5: 4 | G5: 0.15 | H5: 2024-04-14 | I5: 161.7
A6: CUST030 | B6: James Wilson | C6: North | D6: Books | E6: 847 | F6: 12 | G6: 0.2 | H6: 2024-04-15 | I6: 271.04
A7: CUST007 | B7: Michael Anderson | C7: North | D7: Furniture | E7: 965.64 | F7: 8 | G7: 0.1 | H7: 2024-04-16 | I7: 304.18
A8: CUST001 | B8: Linda Wilson | C8: West | D8: Electronics | E8: 1317.53 | F8: 12 | G8: 0.05 | H8: 2024-04-16 | I8: 312.91
A9: CUST026 | B9: Mary Davis | C9: East | D9: Furniture | E9: 1074.47 | F9: 6 | G9: 0.2 | H9: 2024-04-19 | I9: 300.85
A10: CUST009 | B10: Linda Jackson | C10: Central | D10: Books | E10: 501.54 | F10: 11 | G10: 0.05 | H10: 2024-04-19 | I10: 190.59
A11: CUST010 | B11: David Thomas | C11: Central | D11: Clothing | E11: 737.31 | F11: 2 | G11: 0.05 | H11: 2024-04-19 | I11: 350.22
A12: CUST014 | B12: Emma Davis | C12: West | D12: Office Supplies | E12: 1572.82 | F12: 6 | G12: 0.05 | H12: 2024-04-20 | I12: 672.38
A13: CUST014 | B13: David Thomas | C13: Central | D13: Books | E13: 1343.13 | F13: 14 | G13: 0.15 | H13: 2024-04-22 | I13: 456.66
... A201: CUST016 | B201: David Thomas | C201: South | D201: Clothing | E201: 928.32 | F201: 2 | G201: 0.05 | H201: 2025-04-07 | I201: 440.95

Sheet Conditional
A1: Top 10 Customers by Total Purchase
B3: Customer ID | C3: Customer Name | D3: Total Purchase
B4: CUST019 | C4: James Davis | D4: =SUMIF(Data!$A:$A,B4,Data!$E:$E) -> 4640.11
B5: CUST012 | C5: Robert Anderson | D5: =SUMIF(Data!$A:$A,B5,Data!$E:$E) -> 8339
B6: CUST017 | C6: James Taylor | D6: =SUMIF(Data!$A:$A,B6,Data!$E:$E) -> 3419.2
B7: CUST005 | C7: Robert Anderson | D7: =SUMIF(Data!$A:$A,B7,Data!$E:$E) -> 6666.13
B8: CUST030 | C8: James Wilson | D8: =SUMIF(Data!$A:$A,B8,Data!$E:$E) -> 7928.71
B9: CUST007 | C9: Michael Anderson | D9: =SUMIF(Data!$A:$A,B9,Data!$E:$E) -> 9941.88
B10: CUST001 | C10: Linda Wilson | D10: =SUMIF(Data!$A:$A,B10,Data!$E:$E) -> 6549.55
B11: CUST026 | C11: Mary Davis | D11: =SUMIF(Data!$A:$A,B11,Data!$E:$E) -> 9371.81
B12: CUST009 | C12: Linda Jackson | D12: =SUMIF(Data!$A:$A,B12,Data!$E:$E) -> 6505.2
B13: CUST010 | C13: David Thomas | D13: =SUMIF(Data!$A:$A,B13,Data!$E:$E) -> 4259.22
B14: CUST014 | C14: Emma Davis | D14: =SUMIF(Data!$A:$A,B14,Data!$E:$E) -> 6729.89
B15: CUST014 | C15: David Thomas | D15: =SUMIF(Data!$A:$A,B15,Data!$E:$E) -> 6729.89
... B174: CUST016 | C174: David Thomas | D174: =SUMIF(Data!$A:$A,B174,Data!$E:$E) -> 3369.17

Sheet WhatIf
A1: WHAT IF Analysis - Impact of Discount on Profit
A3: Current Scenario
A4: Total Sales: | B4: =SUM(Data!E:E) -> 195217.76
A5: Total Profit: | B5: =SUM(Data!I:I) -> 68287.01
A6: Current Avg Discount: | B6: =AVERAGE(Data!G:G) -> 0.09725
A8: What-If Scenarios
A9: New Discount Rate | B9: Adjusted Sales | C9: Adjusted Profit | D9: Profit Change | E9: Profit Change %
A10: 0 | B10: =SUM(Data!E:E)*(1-A10) -> 195217.76 | C10: =SUM(Data!I:I)*(1-A10/$B$6) -> 68287.01 | D10: =C10-$B$5 -> 0 | E10: =D10/$B$5 -> 0
A11: 0.05 | B11: =SUM(Data!E:E)*(1-A11) -> 185456.87 | C11: =SUM(Data!I:I)*(1-A11/$B$6) -> 33178.007 | D11: =C11-$B$5 -> -35109.003 | E11: =D11/$B$5 -> -0.51413882
A12: 0.1 | B12: =SUM(Data!E:E)*(1-A12) -> 175695.98 | C12: =SUM(Data!I:I)*(1-A12/$B$6) -> -1930.9951 | D12: =C12-$B$5 -> -70218.005 | E12: =D12/$B$5 -> -1.0282776
A13: 0.15 | B13: =SUM(Data!E:E)*(1-A13) -> 165935.1 | C13: =SUM(Data!I:I)*(1-A13/$B$6) -> -37039.998 | D13: =C13-$B$5 -> -105327.01 | E13: =D13/$B$5 -> -1.5424165
A14: 0.2 | B14: =SUM(Data!E:E)*(1-A14) -> 156174.21 | C14: =SUM(Data!I:I)*(1-A14/$B$6) -> -72149 | D14: =C14-$B$5 -> -140436.01 | E14: =D14/$B$5 -> -2.0565553
A15: 0.25 | B15: =SUM(Data!E:E)*(1-A15) -> 146413.32 | C15: =SUM(Data!I:I)*(1-A15/$B$6) -> -107258 | D15: =C15-$B$5 -> -175545.01 | E15: =D15/$B$5 -> -2.5706941

Sheet DescriptiveStats
A1: Descriptive Statistics Summary
A3: Metric | B3: Sales | C3: Quantity | D3: Profit
A4: Mean | B4: =AVERAGE(Data!E:E) -> 976.0888 | C4: =AVERAGE(Data!F:F) -> 9.995 | D4: =AVERAGE(Data!I:I) -> 341.43505
A5: Median | B5: =MEDIAN(Data!E:E) -> 976.72 | C5: =MEDIAN(Data!F:F) -> 10 | D5: =MEDIAN(Data!I:I) -> 332.255
A6: Std Dev | B6: =STDEV(Data!E:E) -> 299.27376 | C6: =STDEV(Data!F:F) -> 5.646627 | D6: =STDEV(Data!I:I) -> 135.76619
A7: Variance | B7: =VAR(Data!E:E) -> 89564.783 | C7: =VAR(Data!F:F) -> 31.884397 | D7: =VAR(Data!I:I) -> 18432.459
A8: Min | B8: =MIN(Data!E:E) -> 258.51 | C8: =MIN(Data!F:F) -> 1 | D8: =MIN(Data!I:I) -> 64.63
A9: Min | B9: =MIN(Data!E:E) -> 258.51 | C9: =MIN(Data!F:F) -> 1 | D9: =MIN(Data!I:I) -> 64.63
A10: Max | B10: =MAX(Data!E:E) -> 1923.66 | C10: =MAX(Data!F:F) -> 19 | D10: =MAX(Data!I:I) -> 769.46
A11: Range | B11: =MAX(Data!E:E)-MIN(Data!E:E) -> 1665.15 | C11: =MAX(Data!F:F)-MIN(Data!F:F) -> 18 | D11: =MAX(Data!I:I)-MIN(Data!I:I) -> 704.83
A12: Count | B12: =COUNTA(Data!E:E) -> 201 | C12: =COUNTA(Data!F:F) -> 201 | D12: =COUNTA(Data!I:I) -> 201

Sheet Storytelling
A1: Monthly Sales Growth Analysis
A3: Month-Year | B3: Total Sales | C3: Growth | D3: Growth %
A4: {=_xlfn.UNIQUE(TEXT(Data!H2:H201,"mmm-yyyy"))} -> Apr-2024 | B4: =SUMIF(A4:A16, A4, Data!E2:E201) -> 1036.09 | C4: - | D4: -
A5: May-2024 | B5: =SUMIF(A5:A17, A5, Data!E3:E202) -> 1101.28 | C5: =B5-B4 -> 65.19 | D5: =IF(B4=0,0,B5/B4) -> 1.0629192
A6: Jun-2024 | B6: =SUMIF(A6:A18, A6, Data!E4:E203) -> 713.34 | C6: =B6-B5 -> -387.94 | D6: =IF(B5=0,0,C6/B5) -> -0.35226282
A7: Jul-2024 | B7: =SUMIF(A7:A19, A7, Data!E5:E204) -> 760.93 | C7: =B7-B6 -> 47.59 | D7: =IF(B6=0,0,C7/B6) -> 0.06671433
A8: Aug-2024 | B8: =SUMIF(A8:A20, A8, Data!E6:E205) -> 847 | C8: =B8-B7 -> 86.07 | D8: =IF(B7=0,0,C8/B7) -> 0.11311159
A9: Sep-2024 | B9: =SUMIF(A9:A21, A9, Data!E7:E206) -> 965.64 | C9: =B9-B8 -> 118.64 | D9: =IF(B8=0,0,C9/B8) -> 0.14007084
A10: Oct-2024 | B10: =SUMIF(A10:A22, A10, Data!E8:E207) -> 1317.53 | C10: =B10-B9 -> 351.89 | D10: =IF(B9=0,0,C10/B9) -> 0.36441117
A11: Nov-2024 | B11: =SUMIF(A11:A23, A11, Data!E9:E208) -> 1074.47 | C11: =B11-B10 -> -243.06 | D11: =IF(B10=0,0,C11/B10) -> -0.18448157
A12: Dec-2024 | B12: =SUMIF(A12:A24, A12, Data!E10:E209) -> 501.54 | C12: =B12-B11 -> -572.93 | D12: =IF(B11=0,0,C12/B11) -> -0.53322103
A13: Jan-2025 | B13: =SUMIF(A13:A25, A13, Data!E11:E210) -> 737.31 | C13: =B13-B12 -> 235.77 | D13: =IF(B12=0,0,C13/B12) -> 0.47009212
A14: Feb-2025 | B14: =SUMIF(A14:A26, A14, Data!E12:E211) -> 1572.82 | C14: =B14-B13 -> 835.51 | D14: =IF(B13=0,0,C14/B13) -> 1.1331869
A15: Mar-2025 | B15: =SUMIF(A15:A27, A15, Data!E13:E212) -> 1343.13 | C15: =B15-B14 -> -229.69 | D15: =IF(B14=0,0,C15/B14) -> -0.14603705
A16: Apr-2025 | B16: =SUMIF(A16:A28, A16, Data!E14:E213) -> 1191.58 | C16: =B16-B15 -> -151.55 | D16: =IF(B15=0,0,C16/B15) -> -0.11283346

Sheet Timestamp
A1: Timestamp Creation with NOW()
A3: Customer ID | B3: Order Date | C3: Sales | D3: Timestamp (NOW)
A4: =Data!A4 -> CUST017 | B4: =Data!H4 -> 2024-04-14 | C4: =Data!E4 -> 713.34 | D4: =NOW() -> 46122.773
A5: =Data!A5 -> CUST005 | B5: =Data!H5 -> 2024-04-14 | C5: =Data!E5 -> 760.93 | D5: =NOW() -> 46122.773
A6: =Data!A6 -> CUST030 | B6: =Data!H6 -> 2024-04-15 | C6: =Data!E6 -> 847 | D6: =NOW() -> 46122.773
A7: =Data!A7 -> CUST007 | B7: =Data!H7 -> 2024-04-16 | C7: =Data!E7 -> 965.64 | D7: =NOW() -> 46122.773
A8: =Data!A8 -> CUST001 | B8: =Data!H8 -> 2024-04-16 | C8: =Data!E8 -> 1317.53 | D8: =NOW() -> 46122.773
A9: =Data!A9 -> CUST026 | B9: =Data!H9 -> 2024-04-19 | C9: =Data!E9 -> 1074.47 | D9: =NOW() -> 46122.773
A10: =Data!A10 -> CUST009 | B10: =Data!H10 -> 2024-04-19 | C10: =Data!E10 -> 501.54 | D10: =NOW() -> 46122.773
A11: =Data!A11 -> CUST010 | B11: =Data!H11 -> 2024-04-19 | C11: =Data!E11 -> 737.31 | D11: =NOW() -> 46122.773
A12: =Data!A12 -> CUST014 | B12: =Data!H12 -> 2024-04-20 | C12: =Data!E12 -> 1572.82 | D12: =NOW() -> 46122.773
A13: =Data!A13 -> CUST014 | B13: =Data!H13 -> 2024-04-22 | C13: =Data!E13 -> 1343.13 | D13: =NOW() -> 46122.773

Sheet HighValue
A1: High-Value Customers (INDEX, MATCH, Filters)
A3: Customer ID | B3: Customer Name | C3: Total Sales | D3: Total Profit | E3: High Value?
A4: CUST019 | B4: James Davis | C4: =SUMIF(Data!$A:$A,A4,Data!$E:$E) -> 4640.11 | D4: =SUMIF(Data!$A:$A,A4,Data!$I:$I) -> 1721.12 | E4: =IF(C4>AVERAGE($C$4:$C$174),"High","Normal") -> Normal
A5: CUST012 | B5: Robert Anderson | C5: =SUMIF(Data!$A:$A,A5,Data!$E:$E) -> 8339 | D5: =SUMIF(Data!$A:$A,A5,Data!$I:$I) -> 2988.71 | E5: =IF(C5>AVERAGE($C$4:$C$174),"High","Normal") -> High
A6: CUST017 | B6: James Taylor | C6: =SUMIF(Data!$A:$A,A6,Data!$E:$E) -> 3419.2 | D6: =SUMIF(Data!$A:$A,A6,Data!$I:$I) -> 1257.21 | E6: =IF(C6>AVERAGE($C$4:$C$174),"High","Normal") -> Normal
A7: CUST005 | B7: Robert Anderson | C7: =SUMIF(Data!$A:$A,A7,Data!$E:$E) -> 6666.13 | D7: =SUMIF(Data!$A:$A,A7,Data!$I:$I) -> 1982.39 | E7: =IF(C7>AVERAGE($C$4:$C$174),"High","Normal") -> Normal
A8: CUST030 | B8: James Wilson | C8: =SUMIF(Data!$A:$A,A8,Data!$E:$E) -> 7928.71 | D8: =SUMIF(Data!$A:$A,A8,Data!$I:$I) -> 2965.48 | E8: =IF(C8>AVERAGE($C$4:$C$174),"High","Normal") -> High
A9: CUST007 | B9: Michael Anderson | C9: =SUMIF(Data!$A:$A,A9,Data!$E:$E) -> 9941.88 | D9: =SUMIF(Data!$A:$A,A9,Data!$I:$I) -> 3936.26 | E9: =IF(C9>AVERAGE($C$4:$C$174),"High","Normal") -> High
A10: CUST001 | B10: Linda Wilson | C10: =SUMIF(Data!$A:$A,A10,Data!$E:$E) -> 6549.55 | D10: =SUMIF(Data!$A:$A,A10,Data!$I:$I) -> 1868.77 | E10: =IF(C10>AVERAGE($C$4:$C$174),"High","Normal") -> Normal
A11: CUST026 | B11: Mary Davis | C11: =SUMIF(Data!$A:$A,A11,Data!$E:$E) -> 9371.81 | D11: =SUMIF(Data!$A:$A,A11,Data!$I:$I) -> 2922.02 | E11: =IF(C11>AVERAGE($C$4:$C$174),"High","Normal") -> High
A12: CUST009 | B12: Linda Jackson | C12: =SUMIF(Data!$A:$A,A12,Data!$E:$E) -> 6505.2 | D12: =SUMIF(Data!$A:$A,A12,Data!$I:$I) -> 2052.54 | E12: =IF(C12>AVERAGE($C$4:$C$174),"High","Normal") -> Normal
A13: CUST010 | B13: David Thomas | C13: =SUMIF(Data!$A:$A,A13,Data!$E:$E) -> 4259.22 | D13: =SUMIF(Data!$A:$A,A13,Data!$I:$I) -> 1529.32 | E13: =IF(C13>AVERAGE($C$4:$C$174),"High","Normal") -> Normal
A14: CUST014 | B14: Emma Davis | C14: =SUMIF(Data!$A:$A,A14,Data!$E:$E) -> 6729.89 | D14: =SUMIF(Data!$A:$A,A14,Data!$I:$I) -> 2507.18 | E14: =IF(C14>AVERAGE($C$4:$C$174),"High","Normal") -> Normal
A15: CUST014 | B15: David Thomas | C15: =SUMIF(Data!$A:$A,A15,Data!$E:$E) -> 6729.89 | D15: =SUMIF(Data!$A:$A,A15,Data!$I:$I) -> 2507.18 | E15: =IF(C15>AVERAGE($C$4:$C$174),"High","Normal") -> Normal
... A174: CUST016 | B174: David Thomas | C174: =SUMIF(Data!$A:$A,A174,Data!$E:$E) -> 3369.17 | D174: =SUMIF(Data!$A:$A,A174,Data!$I:$I) -> 1497.25 | E174: =IF(C174>AVERAGE($C$4:$C$174),"High","Normal") -> Normal

Sheet PivotInstructions
A1: Pivot Table Creation Instructions
A3: Sum of Sales | B3: Column Labels
A4: Row Labels | B4: Books | C4: Clothing | D4: Electronics | E4: Furniture | F4: Office Supplies | G4: Grand Total
A5: Central | B5: 11297.15 | C5: 12200.26 | D5: 6621.24 | E5: 4876.96 | F5: 8472.72 | G5: 43468.33
A6: East | B6: 11389.09 | C6: 2401.45 | D6: 2869.54 | E6: 7592.34 | F6: 8189.22 | G6: 32441.64
A7: North | B7: 8037.01 | C7: 8422.82 | D7: 8191.71 | E7: 6978.08 | F7: 3345.8 | G7: 34975.42
A8: South | B8: 9588.04 | C8: 8393.63 | D8: 11989.07 | E8: 7982.73 | F8: 2295.32 | G8: 40248.79
A9: West | B9: 6691.17 | C9: 10509.43 | D9: 11372.44 | E9: 9182.78 | F9: 6327.76 | G9: 44083.58
A10: Grand Total | B10: 47002.46 | C10: 41927.59 | D10: 41044 | E10: 36612.89 | F10: 28630.82 | G10: 195217.76

Sheet Charts
A1: Chart Creation for KPIs
A3: Sales by Region (Bar Chart)
A4: Region | B4: Total Sales
A5: Central | B5: =SUMIF(Data!$C:$C,A5,Data!$E:$E) -> 43468.33
A6: East | B6: =SUMIF(Data!$C:$C,A6,Data!$E:$E) -> 32441.64
A7: North | B7: =SUMIF(Data!$C:$C,A7,Data!$E:$E) -> 34975.42
A8: South | B8: =SUMIF(Data!$C:$C,A8,Data!$E:$E) -> 40248.79
A9: West | B9: =SUMIF(Data!$C:$C,A9,Data!$E:$E) -> 44083.58
A23: Category | B23: Sales
A24: Books | B24: =SUMIF(Data!$D:$D,A24,Data!$E:$E) -> 47002.46
A25: Clothing | B25: =SUMIF(Data!$D:$D,A25,Data!$E:$E) -> 41927.59
A26: Electronics | B26: =SUMIF(Data!$D:$D,A26,Data!$E:$E) -> 41044
A27: Furniture | B27: =SUMIF(Data!$D:$D,A27,Data!$E:$E) -> 36612.89
A28: Office Supplies | B28: =SUMIF(Data!$D:$D,A28,Data!$E:$E) -> 28630.82

Sheet Dashboard
A1: Sales Analytics Dashboard
A3: 📊 SALES PERFORMANCE DASHBOARD | Apr 2024 – Apr 2025
A5: 💰 TOTAL SALES | D5: 📈 TOTAL PROFIT | G5: 🛒 TOTAL ORDERS | J5: ⭐ AVG ORDER VALUE
A6: =SUM(Data!E:E) -> 195217.76 | D6: =SUM(Data!I:I) -> 68287.01 | G6: =COUNTA(Data!A:A) -> 201 | J6: =SUM(Data!E:E)/COUNTA(Data!A:A) -> 971.23264
A7: =COUNTA(Data!A:A) -> 201 | D7: Margin: 35.0% | G7: Avg: $976/order | J7: Best Region: West
A9: 🏆 TOP CUSTOMER | D9: 📦 TOP CATEGORY | G9: 🌍 TOP REGION | J9: 📉 AVG DISCOUNT
A10: =INDEX(Data!A:A, MATCH(MAX(Data!E:E), Data!E:E, 0)) -> CUST015 | D10: =INDEX(Data!D2:D100, MATCH(MAX(Data!E2:E100), Data!E2:E100, 0)) -> Office Supplies | G10: =INDEX(Data!C2:C100, MATCH(MAX(Data!E2:E100),Data!E2:E100, 0)) -> West | J10: =AVERAGE(Data!G:G) -> 0.09725
A11: $11,611 | D11: $47,002 | G11: $44,084 | J11: Min: 0% | Max: 20%
